{
  "points": [
    {
      "x": 0.09258549972803122,
      "y": 499.7923715039998,
      "z": 0,
      "w": 0.1,
      "h": 0.1
    },
    {
      "x": 8.73128073033299,
      "y": 514.4937481435816,
      "z": 0,
      "w": 0.1,
      "h": 0.1
    },
    {
      "x": 16.944241047985876,
      "y": 525.770995579596,
      "z": 0,
      "w": 0.1,
      "h": 0.1
    },
    {
      "x": 24.89306909612267,
      "y": 536.4379951653464,
      "z": 0,
      "w": 0.1,
      "h": 0.1
    },
    {
      "x": 32.87130744020641,
      "y": 546.6589437977798,
      "z": 0,
      "w": 0.1,
      "h": 0.1
    },
    {
      "x": 41.63893116061366,
      "y": 554.4749174265248,
      "z": 0,
      "w": 0.1,
      "h": 0.1
    },
    {
      "x": 49.699643695539095,
      "y": 560.5459825216785,
      "z": 0,
      "w": 0.1,
      "h": 0.1
    },
    {
      "x": 58.2901430037901,
      "y": 566.2902436447912,
      "z": 0,
      "w": 0.1,
      "h": 0.1
    },
    {
      "x": 67.32154536767241,
      "y": 569.0091019409978,
      "z": 0,
      "w": 0.1,
      "h": 0.1
    },
    {
      "x": 75.23715409535673,
      "y": 571.0823980077814,
      "z": 0,
      "w": 0.1,
      "h": 0.1
    },
    {
      "x": 83.7051977714441,
      "y": 572.4598660597305,
      "z": 0,
      "w": 0.1,
      "h": 0.1
    },
    {
      "x": 92.45585912623875,
      "y": 571.7296549502396,
      "z": 0,
      "w": 0.1,
      "h": 0.1
    },
    {
      "x": 100.39175613991426,
      "y": 569.8715708014604,
      "z": 0,
      "w": 0.1,
      "h": 0.1
    },
    {
      "x": 108.74086413867926,
      "y": 565.8606808850521,
      "z": 0,
      "w": 0.1,
      "h": 0.1
    },
    {
      "x": 117.32318902116899,
      "y": 560.9773429317218,
      "z": 0,
      "w": 0.1,
      "h": 0.1
    },
    {
      "x": 126.30979242564791,
      "y": 554.9059699678326,
      "z": 0,
      "w": 0.1,
      "h": 0.1
    },
    {
      "x": 134.14540113270544,
      "y": 547.3387000449073,
      "z": 0,
      "w": 0.1,
      "h": 0.1
    },
    {
      "x": 141.59611909592007,
      "y": 537.3592937601845,
      "z": 0,
      "w": 0.1,
      "h": 0.1
    },
    {
      "x": 150.24329739535247,
      "y": 526.3188106157347,
      "z": 0,
      "w": 0.1,
      "h": 0.1
    },
    {
      "x": 159.1966930273697,
      "y": 513.2909825220165,
      "z": 0,
      "w": 0.1,
      "h": 0.1
    },
    {
      "x": 167.72780598271865,
      "y": 500.38892115193283,
      "z": 0,
      "w": 0.1,
      "h": 0.1
    },
    {
      "x": 175.6009694377836,
      "y": 486.40817918573595,
      "z": 0,
      "w": 0.1,
      "h": 0.1
    },
    {
      "x": 184.38523275936817,
      "y": 473.67245387056033,
      "z": 0,
      "w": 0.1,
      "h": 0.1
    },
    {
      "x": 192.78184230375766,
      "y": 462.8062592966224,
      "z": 0,
      "w": 0.1,
      "h": 0.1
    },
    {
      "x": 201.00098241426326,
      "y": 453.58524367768723,
      "z": 0,
      "w": 0.1,
      "h": 0.1
    },
    {
      "x": 209.1154750946055,
      "y": 445.48629846642484,
      "z": 0,
      "w": 0.1,
      "h": 0.1
    },
    {
      "x": 217.47186038856753,
      "y": 438.523953646649,
      "z": 0,
      "w": 0.1,
      "h": 0.1
    },
    {
      "x": 226.40583460172817,
      "y": 433.88838159580246,
      "z": 0,
      "w": 0.1,
      "h": 0.1
    },
    {
      "x": 234.4670351395828,
      "y": 430.2252561574237,
      "z": 0,
      "w": 0.1,
      "h": 0.1
    },
    {
      "x": 243.34110832366605,
      "y": 428.12638741040803,
      "z": 0,
      "w": 0.1,
      "h": 0.1
    },
    {
      "x": 251.32203916766036,
      "y": 427.2273515566984,
      "z": 0,
      "w": 0.1,
      "h": 0.1
    },
    {
      "x": 259.6403231348494,
      "y": 427.9181065299597,
      "z": 0,
      "w": 0.1,
      "h": 0.1
    },
    {
      "x": 267.8824488136544,
      "y": 429.9033678176025,
      "z": 0,
      "w": 0.1,
      "h": 0.1
    },
    {
      "x": 276.359937900972,
      "y": 433.5033619005688,
      "z": 0,
      "w": 0.1,
      "h": 0.1
    },
    {
      "x": 284.3900900170307,
      "y": 438.31689238581276,
      "z": 0,
      "w": 0.1,
      "h": 0.1
    },
    {
      "x": 292.74596978287434,
      "y": 444.8273169680704,
      "z": 0,
      "w": 0.1,
      "h": 0.1
    },
    {
      "x": 302.07118082066887,
      "y": 454.0640786481648,
      "z": 0,
      "w": 0.1,
      "h": 0.1
    },
    {
      "x": 309.8581993636557,
      "y": 463.21910050632613,
      "z": 0,
      "w": 0.1,
      "h": 0.1
    },
    {
      "x": 318.0319694759483,
      "y": 473.7620033647305,
      "z": 0,
      "w": 0.1,
      "h": 0.1
    },
    {
      "x": 327.2224160845014,
      "y": 486.36181536879155,
      "z": 0,
      "w": 0.1,
      "h": 0.1
    },
    {
      "x": 334.7055638129557,
      "y": 499.43576978735695,
      "z": 0,
      "w": 0.1,
      "h": 0.1
    },
    {
      "x": 343.4695616437078,
      "y": 514.0081030379794,
      "z": 0,
      "w": 0.1,
      "h": 0.1
    },
    {
      "x": 351.68843541088563,
      "y": 526.1675012166585,
      "z": 0,
      "w": 0.1,
      "h": 0.1
    },
    {
      "x": 360.4359927882714,
      "y": 537.2799458460449,
      "z": 0,
      "w": 0.1,
      "h": 0.1
    },
    {
      "x": 368.3602822588229,
      "y": 546.1359555894684,
      "z": 0,
      "w": 0.1,
      "h": 0.1
    },
    {
      "x": 376.8679230232554,
      "y": 554.38713979975,
      "z": 0,
      "w": 0.1,
      "h": 0.1
    },
    {
      "x": 384.3878782430059,
      "y": 561.0719352849386,
      "z": 0,
      "w": 0.1,
      "h": 0.1
    },
    {
      "x": 393.93979511414267,
      "y": 565.6961955176283,
      "z": 0,
      "w": 0.1,
      "h": 0.1
    },
    {
      "x": 401.7253123473748,
      "y": 569.6859070687102,
      "z": 0,
      "w": 0.1,
      "h": 0.1
    },
    {
      "x": 410.4188136350462,
      "y": 571.7718661832345,
      "z": 0,
      "w": 0.1,
      "h": 0.1
    },
    {
      "x": 418.73438159073936,
      "y": 572.3604243306776,
      "z": 0,
      "w": 0.1,
      "h": 0.1
    },
    {
      "x": 426.89630511874645,
      "y": 571.0561135471654,
      "z": 0,
      "w": 0.1,
      "h": 0.1
    },
    {
      "x": 435.8648477896642,
      "y": 569.2180878608367,
      "z": 0,
      "w": 0.1,
      "h": 0.1
    },
    {
      "x": 444.12343575804283,
      "y": 565.5619919625422,
      "z": 0,
      "w": 0.1,
      "h": 0.1
    },
    {
      "x": 452.30056987963513,
      "y": 560.6470468431673,
      "z": 0,
      "w": 0.1,
      "h": 0.1
    },
    {
      "x": 460.70412377882394,
      "y": 554.386812308675,
      "z": 0,
      "w": 0.1,
      "h": 0.1
    },
    {
      "x": 468.1589685199657,
      "y": 546.7059463843344,
      "z": 0,
      "w": 0.1,
      "h": 0.1
    },
    {
      "x": 477.345284166157,
      "y": 537.0031820556447,
      "z": 0,
      "w": 0.1,
      "h": 0.1
    },
    {
      "x": 485.7456316710773,
      "y": 526.2318561963851,
      "z": 0,
      "w": 0.1,
      "h": 0.1
    },
    {
      "x": 493.67680036304216,
      "y": 513.0005158217753,
      "z": 0,
      "w": 0.1,
      "h": 0.1
    },
    {
      "x": 502.73276315525743,
      "y": 499.770314515081,
      "z": 0,
      "w": 0.1,
      "h": 0.1
    },
    {
      "x": 511.2137187578659,
      "y": 486.2549060625156,
      "z": 0,
      "w": 0.1,
      "h": 0.1
    },
    {
      "x": 519.2515270775011,
      "y": 473.88545755078104,
      "z": 0,
      "w": 0.1,
      "h": 0.1
    },
    {
      "x": 526.8698707268695,
      "y": 462.5522188673562,
      "z": 0,
      "w": 0.1,
      "h": 0.1
    },
    {
      "x": 536.4740878552813,
      "y": 453.52464749472546,
      "z": 0,
      "w": 0.1,
      "h": 0.1
    },
    {
      "x": 543.6050135077688,
      "y": 445.77627800345505,
      "z": 0,
      "w": 0.1,
      "h": 0.1
    },
    {
      "x": 552.8482265693639,
      "y": 438.3766199574765,
      "z": 0,
      "w": 0.1,
      "h": 0.1
    },
    {
      "x": 561.5034940582492,
      "y": 433.45068701900215,
      "z": 0,
      "w": 0.1,
      "h": 0.1
    },
    {
      "x": 569.8383532334544,
      "y": 431.0585083673783,
      "z": 0,
      "w": 0.1,
      "h": 0.1
    },
    {
      "x": 577.2135548092385,
      "y": 428.92282797434905,
      "z": 0,
      "w": 0.1,
      "h": 0.1
    },
    {
      "x": 586.2543019736148,
      "y": 427.42663402855374,
      "z": 0,
      "w": 0.1,
      "h": 0.1
    },
    {
      "x": 595.3126197731714,
      "y": 428.7071675768851,
      "z": 0,
      "w": 0.1,
      "h": 0.1
    },
    {
      "x": 602.6690754045418,
      "y": 430.25458053185685,
      "z": 0,
      "w": 0.1,
      "h": 0.1
    },
    {
      "x": 610.6045956836344,
      "y": 433.99157590512067,
      "z": 0,
      "w": 0.1,
      "h": 0.1
    },
    {
      "x": 619.649563749875,
      "y": 439.07965516757673,
      "z": 0,
      "w": 0.1,
      "h": 0.1
    },
    {
      "x": 627.5921859681142,
      "y": 446.174879640189,
      "z": 0,
      "w": 0.1,
      "h": 0.1
    },
    {
      "x": 636.2592310828126,
      "y": 453.16514974873127,
      "z": 0,
      "w": 0.1,
      "h": 0.1
    },
    {
      "x": 645.344056886946,
      "y": 462.7704172099069,
      "z": 0,
      "w": 0.1,
      "h": 0.1
    },
    {
      "x": 653.1597015656841,
      "y": 473.74887533622643,
      "z": 0,
      "w": 0.1,
      "h": 0.1
    },
    {
      "x": 661.3749891891566,
      "y": 486.309892687479,
      "z": 0,
      "w": 0.1,
      "h": 0.1
    },
    {
      "x": 670.2749489767189,
      "y": 500.94528436563655,
      "z": 0,
      "w": 0.1,
      "h": 0.1
    },
    {
      "x": 678.4459695093542,
      "y": 514.4992478286981,
      "z": 0,
      "w": 0.1,
      "h": 0.1
    },
    {
      "x": 686.5136631111129,
      "y": 525.645812778437,
      "z": 0,
      "w": 0.1,
      "h": 0.1
    },
    {
      "x": 694.4751489579668,
      "y": 537.5888714691825,
      "z": 0,
      "w": 0.1,
      "h": 0.1
    },
    {
      "x": 702.8429284058478,
      "y": 546.706591974376,
      "z": 0,
      "w": 0.1,
      "h": 0.1
    },
    {
      "x": 712.8459542983404,
      "y": 554.4179479169411,
      "z": 0,
      "w": 0.1,
      "h": 0.1
    },
    {
      "x": 720.8042233511327,
      "y": 561.4308757711378,
      "z": 0,
      "w": 0.1,
      "h": 0.1
    },
    {
      "x": 728.6622644651145,
      "y": 565.8959896893892,
      "z": 0,
      "w": 0.1,
      "h": 0.1
    },
    {
      "x": 736.939547827294,
      "y": 569.6717735433062,
      "z": 0,
      "w": 0.1,
      "h": 0.1
    },
    {
      "x": 745.3872427107842,
      "y": 571.8085661068857,
      "z": 0,
      "w": 0.1,
      "h": 0.1
    },
    {
      "x": 753.6335794658901,
      "y": 572.3870354140644,
      "z": 0,
      "w": 0.1,
      "h": 0.1
    },
    {
      "x": 761.9968673070016,
      "y": 571.9192638494218,
      "z": 0,
      "w": 0.1,
      "h": 0.1
    },
    {
      "x": 770.7577725526521,
      "y": 569.211591564812,
      "z": 0,
      "w": 0.1,
      "h": 0.1
    },
    {
      "x": 779.8231699367499,
      "y": 566.2857872165893,
      "z": 0,
      "w": 0.1,
      "h": 0.1
    },
    {
      "x": 787.4488051167449,
      "y": 560.7038663800113,
      "z": 0,
      "w": 0.1,
      "h": 0.1
    },
    {
      "x": 795.1086268086796,
      "y": 553.9194084956489,
      "z": 0,
      "w": 0.1,
      "h": 0.1
    },
    {
      "x": 803.4251992733168,
      "y": 546.9241967869942,
      "z": 0,
      "w": 0.1,
      "h": 0.1
    },
    {
      "x": 812.8036865374355,
      "y": 536.807288947339,
      "z": 0,
      "w": 0.1,
      "h": 0.1
    },
    {
      "x": 820.8664240978866,
      "y": 526.0435677085,
      "z": 0,
      "w": 0.1,
      "h": 0.1
    },
    {
      "x": 829.7702008592033,
      "y": 513.3871462783208,
      "z": 0,
      "w": 0.1,
      "h": 0.1
    },
    {
      "x": 836.8930104670777,
      "y": 499.8316151398255,
      "z": 0,
      "w": 0.1,
      "h": 0.1
    },
    {
      "x": 846.9212478003764,
      "y": 484.1513110653266,
      "z": 0,
      "w": 0.1,
      "h": 0.1
    },
    {
      "x": 855.4432065112297,
      "y": 470.22613669141276,
      "z": 0,
      "w": 0.1,
      "h": 0.1
    },
    {
      "x": 865.4847671125716,
      "y": 458.36385873671236,
      "z": 0,
      "w": 0.1,
      "h": 0.1
    },
    {
      "x": 875.2787807993088,
      "y": 448.61319636017083,
      "z": 0,
      "w": 0.1,
      "h": 0.1
    },
    {
      "x": 883.7016745599883,
      "y": 439.4660285525775,
      "z": 0,
      "w": 0.1,
      "h": 0.1
    },
    {
      "x": 892.8644378390348,
      "y": 432.39068179064907,
      "z": 0,
      "w": 0.1,
      "h": 0.1
    },
    {
      "x": 902.3085968221532,
      "y": 427.4706091758603,
      "z": 0,
      "w": 0.1,
      "h": 0.1
    },
    {
      "x": 910.7385018365902,
      "y": 424.7382600547287,
      "z": 0,
      "w": 0.1,
      "h": 0.1
    },
    {
      "x": 920.2952244906928,
      "y": 422.97564769405625,
      "z": 0,
      "w": 0.1,
      "h": 0.1
    },
    {
      "x": 927.9679617598039,
      "y": 423.1731141933069,
      "z": 0,
      "w": 0.1,
      "h": 0.1
    },
    {
      "x": 937.4510140588147,
      "y": 425.53859911005696,
      "z": 0,
      "w": 0.1,
      "h": 0.1
    },
    {
      "x": 944.4383700048612,
      "y": 429.5689556023743,
      "z": 0,
      "w": 0.1,
      "h": 0.1
    },
    {
      "x": 953.1706713133347,
      "y": 435.63860969251704,
      "z": 0,
      "w": 0.1,
      "h": 0.1
    },
    {
      "x": 962.3539943979233,
      "y": 442.10116178271346,
      "z": 0,
      "w": 0.1,
      "h": 0.1
    },
    {
      "x": 970.6771303407938,
      "y": 451.7386803741412,
      "z": 0,
      "w": 0.1,
      "h": 0.1
    },
    {
      "x": 977.8397564407546,
      "y": 461.94504449990967,
      "z": 0,
      "w": 0.1,
      "h": 0.1
    },
    {
      "x": 985.8338742495448,
      "y": 475.68191392741494,
      "z": 0,
      "w": 0.1,
      "h": 0.1
    },
    {
      "x": 994.3092077826666,
      "y": 489.64259074898996,
      "z": 0,
      "w": 0.1,
      "h": 0.1
    },
    {
      "x": 1002.5755241048054,
      "y": 506.83076080354573,
      "z": 0,
      "w": 0.1,
      "h": 0.1
    }
  ]
}